README.md
sheets_for_person_schema/datamodel/__init__.py
sheets_for_person_schema/datamodel/sheets_for_person_schema.py
sheets_for_person_schema/schema/personinfo_enums.yaml
sheets_for_person_schema/schema/sheets_for_person_schema.yaml
sheets_for_person_schema-0.1.0.dist-info/LICENSE
sheets_for_person_schema-0.1.0.dist-info/WHEEL
sheets_for_person_schema-0.1.0.dist-info/METADATA
sheets_for_person_schema-0.1.0.dist-info/RECORD
