Metadata-Version: 2.1
Name: sheets-for-person-schema
Version: 0.1.0
Summary: Files for schemasheets exercises at ICBO 2022
License: MIT
Author: Mark Andrew Miller
Author-email: mam@lbl.gov
Requires-Python: >=3.9,<4.0
Classifier: License :: OSI Approved :: MIT License
Classifier: Programming Language :: Python :: 3
Classifier: Programming Language :: Python :: 3.10
Classifier: Programming Language :: Python :: 3.9
Provides-Extra: docs
Requires-Dist: linkml-runtime (>=1.1.24,<2.0.0)
